setup.py
swmmhub/__init__.py
swmmhub.egg-info/PKG-INFO
swmmhub.egg-info/SOURCES.txt
swmmhub.egg-info/dependency_links.txt
swmmhub.egg-info/top_level.txt